<!-- original file -->
<skin>
<!-- cf#_#start -->
	<!-- MetrixHD v2.5 by iMaxxx | optimized for openATV 4.0 -->
	<!-- MetrixHD v3.0 by openATV Team  -->
	<!-- recommended to use with XPicons -->
	<!-- Explicitly, no one is allowed to use any version of the Skin with other team Images -->
	<!-- You can modify and redistribute it as long as you keep this license and the original author for the skin and all of your modifications -->
	<!-- check controlflags.md -->
	<output id="0">
		<resolution xres="1280" yres="720" bpp="32" />
	</output>
	<colors>
		<color name="foreground" value="#00ffffff" />
		<color name="background" value="#40000000" />
		<color name="rds_text_bg" value="#00003258" />
		<color name="rssviewtop" value="#45005050" />
		<color name="transparent" value="#ff111111" />
		<color name="transpBlack" value="#80000000" />
		<color name="transpWhite" value="#77ffffff" />
		<color name="transpyellow" value="#33bab329" />
		<color name="black" value="#00000000" />
		<color name="dark" value="#00294a6b" />
		<color name="darkgrey" value="#00999999" />
		<color name="grey" value="#00bbbbbb" />
		<color name="orange" value="#00f47d19" />
		<color name="white" value="#00ffffff" />
		<color name="blue" value="#000064c7" />										<!-- MetrixColors - Color Button Blue -->
		<color name="green" value="#00389416" />									<!-- MetrixColors - Color Button Green -->
		<color name="red" value="#00f23d21" />										<!-- MetrixColors - Color Button Red -->
		<color name="yellow" value="#00e5b243" />									<!-- MetrixColors - Color Button Yellow -->
		<color name="layer-a-channelselection-foreground" value="#00FFFFFF" />		<!-- MetrixColors - Foreground Channelselection layer a -->
		<color name="layer-a-channelselection-foregroundColorSelected" value="#00FFFFFF" />					<!-- MetrixColors - Foreground Selected Channelselection layer a -->
		<color name="layer-a-channelselection-foreground-ServiceDescription" value="#00BDBDBD" />			<!-- MetrixColors - Foreground Service Description Channelselection layer a -->
		<color name="layer-a-channelselection-foreground-ServiceDescriptionSelected" value="#00FFFFFF" />	<!-- MetrixColors - Foreground Service Description Selected Channelselection layer a -->
		<color name="layer-a-channelselection-foreground-colorServiceRecorded" value="#00E51400" />			<!-- MetrixColors - Foreground Service colorServiceRecorded Channelselection layer a -->
		<color name="layer-a-channelselection-foreground-colorServicePseudoRecorded" value="#000000CD" />	<!-- MetrixColors - Foreground Service colorServicePseudoRecorded Channelselection layer a -->
		<color name="layer-a-channelselection-foreground-colorServiceStreamed" value="#00C3461B" />			<!-- MetrixColors - Foreground Service colorServiceStreamed Channelselection layer a -->
		<color name="layer-a-channelselection-progressbar" value="#00BDBDBD" />
		<color name="layer-a-channelselection-progressbarborder" value="#00BDBDBD" />
		<color name="layer-a-foreground" value="#00FFFFFF" />						<!-- MetrixColors - Foreground layer a -->
		<color name="layer-a-background" value="#1A0F0F0F" />						<!-- MetrixColors - Background layer a -->
		<color name="layer-a-selection-foreground" value="#00FFFFFF" />				<!-- MetrixColors - Foreground layer a for selected items -->
		<color name="layer-a-selection-background" value="#1A27408B" />				<!-- MetrixColors - Background layer a for selected items -->
		<color name="layer-a-accent1" value="#00BDBDBD" />							<!-- MetrixColors - First accent layer a -->
		<color name="layer-a-accent2" value="#006E6E6E" />							<!-- MetrixColors - Second accent layer a -->
		<color name="layer-a-extendedinfo1" value="#00BDBDBD" />					<!-- MetrixColors - First extended info layer a -->
		<color name="layer-a-extendedinfo2" value="#006E6E6E" />					<!-- MetrixColors - Second extended info layer a -->
		<color name="layer-a-progress" value="#1A27408B" />							<!-- MetrixColors - Progress layer a -->
		<color name="layer-a-underline" value="#00BDBDBD" />						<!-- MetrixColors - color underline screen title text -->
		<color name="layer-b-foreground" value="#00FFFFFF" />						<!-- MetrixColors - Foreground layer b -->
		<color name="layer-b-background" value="#1A27408B" />						<!-- MetrixColors - Background layer b -->
		<color name="layer-b-selection-foreground" value="#00FFFFFF" />				<!-- MetrixColors - Foreground layer b for selected items -->
		<color name="layer-b-selection-background" value="#1A0F0F0F" />				<!-- MetrixColors - Background layer b for selected items -->
		<color name="layer-b-accent1" value="#00BDBDBD" />							<!-- MetrixColors - First accent layer b -->
		<color name="layer-b-accent2" value="#006E6E6E" />							<!-- MetrixColors - Second accent layer b -->
		<color name="layer-b-progress" value="#1AFFFFFF" />							<!-- MetrixColors - Progress layer b -->
		<color name="background-text" value="#34FFFFFF" />							<!-- MetrixColors - Primary color for texts in background -->
		<color name="text-background" value="#67FFFFFF" />							<!-- MetrixColors - Background color for texts in background -->
		<color name="title-foreground" value="#00FFFFFF" />							<!-- MetrixColors - Foreground color for window title -->
		<color name="title-background" value="#000F0F0F" />							<!-- MetrixColors - Background color for window title -->
		<color name="epg-eventdescription-foreground" value="#00FFFFFF" />			<!-- MetrixColors - Graphical and Vertivcal EPG Event description font color -->
		<color name="epg-eventdescription-background" value="#1A27408B" />			<!-- MetrixColors - Graphical and Vertivcal EPG Event description background color -->
		<color name="epg-background" value="#1A0F0F0F" />							<!-- MetrixColors - Graphical and Vertivcal EPG layer back color -->
		<color name="epg-event-foreground" value="#00FFFFFF" />						<!-- MetrixColors - Graphical and Vertivcal EPG Event font color -->
		<color name="epg-event-background" value="#1A0F0F0F" />						<!-- MetrixColors - Graphical and Vertivcal EPG Event back color -->
		<color name="epg-event-now-foreground" value="#00FFFFFF" />					<!-- MetrixColors - Graphical and Vertivcal EPG Event now font color -->
		<color name="epg-event-now-background" value="#1A000000" />					<!-- MetrixColors - Graphical and Vertivcal EPG Event now back color -->
		<color name="epg-event-selected-foreground" value="#00FFFFFF" />			<!-- MetrixColors - Graphical and Vertivcal EPG Event selected font color -->
		<color name="epg-event-selected-background" value="#1A27408B" />			<!-- MetrixColors - Graphical and Vertivcal EPG Event selected back color -->
		<color name="epg-service-foreground" value="#00FFFFFF" />					<!-- MetrixColors - Graphical and Vertivcal EPG Event font color -->
		<color name="epg-service-background" value="#1A0F0F0F" />					<!-- MetrixColors - Graphical and Vertivcal EPG Service back color -->
		<color name="epg-service-now-foreground" value="#00FFFFFF" />				<!-- MetrixColors - Graphical and Vertivcal EPG Servive now font color -->
		<color name="epg-service-now-background" value="#1A27408B" />				<!-- MetrixColors - Graphical and Vertivcal EPG Servive now back color -->
		<color name="epg-timeline-foreground" value="#00F0A30A" />					<!-- MetrixColors - Graphical and Vertivcal EPG timeline font color -->
		<color name="epg-timeline-background" value="#1A000000" />					<!-- MetrixColors - Graphical and Vertivcal EPG timeline back color -->
		<color name="epg-primetime-foreground" value="#00008A00" />					<!-- MetrixColors - Graphical and Vertivcal EPG Primetime font color -->
		<color name="epg-primetime-background" value="#1A0F0F0F" />					<!-- MetrixColors - Graphical and Vertivcal EPG Primetime back color -->
		<color name="epg-borderlines" value="#1ABDBDBD" />							<!-- MetrixColors - Graphical and Vertivcal EPG border line color -->
		<color name="layer-a-title-foreground" value="#00FFFFFF" />					<!-- MetrixColors - Foreground color for window title in layer a -->
		<color name="layer-a-button-foreground" value="#00FFFFFF" />				<!-- MetrixColors - Foreground color for button description in layer a -->
		<color name="layer-a-clock-foreground" value="#00FFFFFF" />					<!-- MetrixColors - Foreground color for clock in layer a -->
		<color name="layer-b-clock-foreground" value="#00FFFFFF" />					<!-- MetrixColors - Foreground color for clock in layer b -->
		<color name="weather-borderlines" value="#00FFFFFF" />						<!-- MetrixColors - Weather border line color -->
		<color name="menubackground" value="#1A0F0F0F" />							<!-- MetrixColors - Background color for menu -->
		<color name="menusymbolbackground" value="#1A27408B" />						<!-- MetrixColors - Background color for menu symbol -->
		<color name="menufont" value="#00FFFFFF" />									<!-- MetrixColors - Font color for menu item  -->
		<color name="menufontselected" value="#00FFFFFF" />							<!-- MetrixColors - Font color for selected menu item -->
		<color name="infobarbackground" value="#1A0F0F0F" />						<!-- MetrixColors - Background color for infobar,moviebar -->
		<color name="infobarprogress" value="#1A27408B" />							<!-- MetrixColors - Progressbar color for infobar,moviebar -->
		<color name="infobarfont1" value="#00FFFFFF" />								<!-- MetrixColors - Font 1 color for infobar,moviebar -->
		<color name="infobarfont2" value="#00BDBDBD" />								<!-- MetrixColors - Font 2 color for infobar,moviebar -->
		<color name="infobaraccent1" value="#00BDBDBD" />							<!-- MetrixColors - AccentFont 1 color for infobar,moviebar -->
		<color name="infobaraccent2" value="#006E6E6E" />							<!-- MetrixColors - AccentFont 2 color for infobar,moviebar -->
		<color name="scrollbarSlidercolor" value="#00FFFFFF" />
		<color name="scrollbarSliderbordercolor" value="#0027408B" />
		<color name="un18080911" value="#18080911" />
		<color name="un1c202b" value="#001c202b" />
		<color name="un1f771f" value="#001f771f" />
		<color name="un240e1014" value="#240e1014" />
		<color name="un44000000" value="#44000000" />
		<color name="un444444" value="#00444444" />
		<color name="un555555" value="#00555555" />
		<color name="un5678a4" value="#005678a4" />
		<color name="un56c856" value="#0056c856" />
		<color name="un666666" value="#00666666" />
		<color name="un800000" value="#00800000" />
		<color name="un808888" value="#00808888" />
		<color name="un9f1313" value="#009f1313" />
		<color name="unbab329" value="#00bab329" />
		<color name="und3d3d3" value="#00d3d3d3" />
		<color name="undcaaaa" value="#00dcaaaa" />
		<color name="undcdcdc" value="#00dcdcdc" />
		<color name="unececec" value="#00ececec" />
		<color name="unf0b400" value="#00f0b400" />
		<color name="unfcc000" value="#00fcc000" />
		<color name="unff" value="#000000ff" />
		<color name="unff00" value="#0000ff00" />
		<color name="unff0000" value="#00ff0000" />
		<color name="unff000000" value="#ff000000" />
		<color name="unff4a3c" value="#00ff4a3c" />
		<color name="unffff00" value="#00ffff00" />
		<color name="unffffff" value="#00ffffff" />
	</colors>
	<fonts>
		<font filename="/usr/share/fonts/lcd.ttf" name="LCD" scale="100" />
		<font filename="/usr/share/fonts/ae_AlMateen.ttf" name="Replacement" scale="100" replacement="1" />
		<font filename="/usr/share/fonts/tuxtxt.ttf" name="Console" scale="100" />
		<font filename="/usr/share/fonts/andale.ttf" name="Fixed" scale="100" />
		<font filename="/usr/share/fonts/nmsbd.ttf" name="Arial" scale="100" />
		<font filename="/usr/share/fonts/DejaVuSans.ttf" name="DejaVuSans" scale="100" />
		<font filename="/usr/share/enigma2/MetrixHD/fonts/OpenSans-Regular.ttf" name="Regular" scale="95" />
		<font filename="/usr/share/enigma2/MetrixHD/fonts/OpenSans-Regular.ttf" name="RegularLight" scale="95" />
		<font filename="/usr/share/enigma2/MetrixHD/fonts/setrixHD.ttf" name="SetrixHD" scale="100" />
		<font filename="/usr/share/enigma2/MetrixHD/fonts/MetrixIcons.ttf" name="MetrixIcons" scale="100" />
<!-- for individual skinned screens -->
	<!-- global -->
		<font filename="/usr/share/enigma2/MetrixHD/fonts/setrixHD.ttf" name="global_title" scale="100" />				<!--Screen or window title-->
		<font filename="/usr/share/enigma2/MetrixHD/fonts/setrixHD.ttf" name="global_button" scale="90" />				<!--Button text-->
		<font filename="/usr/share/enigma2/MetrixHD/fonts/setrixHD.ttf" name="global_clock" scale="100" />				<!--Clock text-->
		<font filename="/usr/share/enigma2/MetrixHD/fonts/DroidSans-Bold.ttf" name="global_weather_bold" scale="100" />	<!--Weather Weekday text-->
		<font filename="/usr/share/enigma2/MetrixHD/fonts/setrixHD.ttf" name="global_large" scale="100" />				<!--Text in background or large text-->
		<font filename="/usr/share/enigma2/MetrixHD/fonts/setrixHD.ttf" name="global_large_screen" scale="100" />		<!--Text in background or large text-->
		<font filename="/usr/share/enigma2/MetrixHD/fonts/setrixHD.ttf" name="global_large_menu" scale="100" />			<!--Text in background or large text-->
		<font filename="/usr/share/enigma2/MetrixHD/fonts/OpenSans-Regular.ttf" name="global_small" scale="95" />		<!--Small text in Infobar, Screens ...-->
		<font filename="/usr/share/enigma2/MetrixHD/fonts/setrixHD.ttf" name="global_menu" scale="100" />				<!--Menu items-->
	<!-- screens, plugins -->
		<font filename="/usr/share/enigma2/MetrixHD/fonts/OpenSans-Regular.ttf" name="screen_label" scale="95" />		<!--Label Name-->
		<font filename="/usr/share/enigma2/MetrixHD/fonts/OpenSans-Regular.ttf" name="screen_text" scale="95" />		<!--Output Text-->
		<font filename="/usr/share/enigma2/MetrixHD/fonts/setrixHD.ttf" name="screen_info" scale="100" />				<!--Info or Description-->
	<!-- epg, channellist, movielist -->
		<font filename="/usr/share/enigma2/MetrixHD/fonts/OpenSans-Regular.ttf" name="epg_event" scale="95" />			<!--Event/Service Name-->
		<font filename="/usr/share/enigma2/MetrixHD/fonts/OpenSans-Regular.ttf" name="epg_text" scale="95" />			<!--Other Text-->
		<font filename="/usr/share/enigma2/MetrixHD/fonts/OpenSans-Regular.ttf" name="epg_info" scale="95" />			<!--Info or Description-->
	<!-- infobar, movieplayer -->
		<font filename="/usr/share/enigma2/MetrixHD/fonts/setrixHD.ttf" name="infobar_event" scale="100" />				<!--Event/Service Name-->
		<font filename="/usr/share/enigma2/MetrixHD/fonts/OpenSans-Regular.ttf" name="infobar_text" scale="95" />		<!--Other Text-->
	<!-- aliases -->
		<alias name="Body" font="screen_text" size="20" height="30" />
		<alias name="ChoiceList" font="screen_text" size="20" height="30" />
		<alias name="Dreamexplorer" font="screen_text" size="20" height="30" />
		<alias name="SelectionList" font="screen_text" size="20" height="30" />
		<alias name="ServiceInfo" font="screen_text" size="20" height="30" />
		<alias name="FileList" font="screen_text" size="20" height="30" />
		<alias name="FileListMulti" font="screen_text" size="20" height="30" />
		<alias name="TextNormal" font="screen_text" size="20" height="30" />
		<alias name="PluginBrowser0" font="screen_text" size="20" height="30" />
		<alias name="PluginBrowser1" font="screen_text" size="18" />
		<alias name="PlayList" font="screen_text" size="18" height="30" />
		<alias name="HelpMenuListExt0" font="screen_text" size="20" height="30" />
		<alias name="HelpMenuListExt1" font="screen_text" size="18"/>
		<alias name="HelpMenuList" font="screen_text" size="20" height="30" />
		<alias name="VirtualKeyBoard" font="screen_text" size="28" height="45" />
	</fonts>
	<subtitles>
		<sub name="Subtitle_TTX" font="Regular;30" shadowColor="#40101010" shadowOffset="3,3" borderWidth="3" />
		<sub name="Subtitle_Regular" font="Regular;30" foregroundColor="undcdcdc" shadowColor="#40101010" shadowOffset="3,3" borderWidth="3" />
		<sub name="Subtitle_Bold" font="Replacement;30" foregroundColor="undcdcdc" shadowColor="#40101010" shadowOffset="3,3" borderWidth="3" />
		<sub name="Subtitle_Italic" font="Regular;30" foregroundColor="undcaaaa" shadowColor="#40101010" shadowOffset="3,3" borderWidth="3" />
	</subtitles>
	<windowstyle type="skinned" id="0">
		<title offset="5,0" font="global_title;34" />
		<configList entryFont="screen_text;19" valueFont="screen_text;18" />
		<color name="Background" color="layer-a-background" />
		<color name="LabelForeground" color="layer-a-foreground" />
		<color name="ListboxBackground" color="layer-a-background" />
		<color name="ListboxForeground" color="layer-a-foreground" />
		<color name="ListboxSelectedBackground" color="layer-a-selection-background" />
		<color name="ListboxSelectedForeground" color="layer-a-foreground" />
		<color name="ListboxMarkedBackground" color="green" />
		<color name="ListboxMarkedForeground" color="layer-a-foreground" />
		<color name="ListboxMarkedAndSelectedBackground" color="blue" />
		<color name="ListboxMarkedAndSelectedForeground" color="layer-a-foreground" />
		<color name="WindowTitleForeground" color="title-foreground" />
		<color name="WindowTitleBackground" color="title-background"/>
		<color name="ScrollbarForeground" color="scrollbarSlidercolor" />
		<color name="ScrollbarBorder" color="scrollbarSliderbordercolor" />
		<color name="SliderForeground" color="scrollbarSlidercolor" />
		<color name="SliderBorder" color="scrollbarSliderbordercolor" />

<!-- cf#_#stop -->
		<borderset name="bsWindow">
			<!--pixmap pos="bpTopLeft" filename="MetrixHD/border/5px/0F0F0F.png" /-->
			<pixmap pos="bpTop" filename="MetrixHD/border/50px/0F0F0F.png" />
			<!--pixmap pos="bpTopRight" filename="MetrixHD/border/5px/0F0F0F.png" /-->
			<pixmap pos="bpLeft" filename="MetrixHD/border/5px/0F0F0F.png" />
			<pixmap pos="bpRight" filename="MetrixHD/border/5px/0F0F0F.png" />
			<!--pixmap pos="bpBottomLeft" filename="MetrixHD/border/5px/0F0F0F.png" /-->
			<pixmap pos="bpBottom" filename="MetrixHD/border/5px/0F0F0F.png" />
			<!--pixmap pos="bpBottomRight" filename="MetrixHD/border/5px/0F0F0F.png" /-->
		</borderset>
		<borderset name="bsListboxEntry">
			<!--lb pixmap pos="bpTop" filename="MetrixHD/border/1px/FFFFFF.png" /-->
			<!--lb pixmap pos="bpBottom" filename="MetrixHD/border/1px/FFFFFF.png" /-->
			<!--lb pixmap pos="bpLeft" filename="MetrixHD/border/1px/FFFFFF.png" /-->
			<!--lb pixmap pos="bpRight" filename="MetrixHD/border/1px/FFFFFF.png" /-->
		</borderset>

		<!-- <slider borderWidth="0" /> -->
		<scrolllabel scrollbarWidth="10" scrollbarBorderWidth="1" scrollbarOffset="5" />
		<listbox scrollbarWidth="10" scrollbarBorderWidth="1" pageSize="0" scrollbarOffset="5"/>
		<!-- 
		TODO TEST showOnDemand as default
		<scrolllabel scrollbarWidth="10" scrollbarBorderWidth="1" scrollbarMode="showOnDemand"/>
		<listbox scrollbarWidth="10" scrollbarBorderWidth="1" enableWrapAround="1" scrollbarMode="showOnDemand"/>
		-->

	</windowstyle>
	<windowstyle type="skinned" id="1">
		<color name="Background" color="layer-a-background" />
		<color name="LabelForeground" color="layer-a-foreground" />
		<color name="ListboxBackground" color="layer-a-background" />
		<color name="ListboxForeground" color="layer-a-foreground" />
		<color name="ListboxSelectedBackground" color="layer-a-selection-background" />
		<color name="ListboxSelectedForeground" color="layer-a-foreground" />
		<color name="ListboxMarkedBackground" color="blue" />
		<color name="ListboxMarkedForeground" color="layer-a-foreground" />
		<color name="ListboxMarkedAndSelectedBackground" color="blue" />
		<color name="ListboxMarkedAndSelectedForeground" color="layer-a-foreground" />
		<color name="WindowTitleForeground" color="title-foreground" />
		<color name="WindowTitleBackground" color="title-background"/>
		<color name="ScrollbarForeground" color="layer-a-foreground" />
		<color name="ScrollbarBorder" color="layer-a-foreground" />
	</windowstyle>
<!-- cf#_#start -->
	<switchpixmap>
		<pixmap name="menu_on" filename="MetrixHD/icons/menu_on.png" />
		<pixmap name="menu_off" filename="MetrixHD/icons/menu_off.png" />
	</switchpixmap>
	<parameters>
		<parameter name="AllowUserDatesAndTimes" value="1,1"/>
		<parameter name="AutotimerEnabledIcon" value="5,2,25,25"/>
		<parameter name="AutotimerRecordIcon" value="32,5,20,20"/>
		<parameter name="DreamexplorerName" value="40,0,660,30"/>
		<parameter name="DreamexplorerIcon" value="10,4,22,22"/>
		<parameter name="PluginBrowserName" value="120,2,30"/>
		<parameter name="PluginBrowserDescr" value="120,24,26"/>
		<parameter name="PluginBrowserIcon" value="10,5,100,40"/>
		<parameter name="PluginBrowserDownloadName" value="80,2,30"/>
		<parameter name="PluginBrowserDownloadDescr" value="80,24,30"/>
		<parameter name="PluginBrowserDownloadIcon" value="10,0,60,50"/>
		<parameter name="ChoicelistDash" value="0,2,700,2"/>
		<parameter name="ChoicelistName" value="50,0,650,38"/>
		<parameter name="ChoicelistIcon" value="10,3,30,30"/>
		<parameter name="ChoicelistIconVerticalline" value="10,0,30,38"/>
		<parameter name="ChoicelistIconExpanded" value="10,3,30,35"/>
		<parameter name="ChoicelistNameSingle" value="10,0,690,38"/>
		<parameter name="ChoicelistVerticalAlignment" value="*center" />
		<parameter name="ConfigListSlider" value="10,0"/>
		<parameter name="ConfigListSeperator" value="400"/>
		<parameter name="FileListName" value="40,2,660,28"/>
		<parameter name="FileListIcon" value="10,4,20,20"/>
		<parameter name="FileListMultiName" value="60,2,640,28"/>
		<parameter name="FileListMultiIcon" value="30,4,20,20"/>
		<parameter name="FileListMultiLock" value="2,0,25,25"/>
		<parameter name="HelpMenuListExtHlp0" value="0,0,700,28"/>
		<parameter name="HelpMenuListExtHlp1" value="0,27,700,23"/>
		<parameter name="HelpMenuListHlp" value="0,0,700,30"/>
		<parameter name="SelectionListDescr" value="40,2,660,30"/>
		<parameter name="SelectionListLock" value="10,2,27,24"/>
		<parameter name="SelectionListLockOff" value="10,2,25,24"/>
		<parameter name="PicturePlayerThumb" value="35,190,30,200,20,14"/>
		<parameter name="PlayListName" value="40,2,660,30"/>
		<parameter name="PlayListIcon" value="10,7,16,16"/>
		<parameter name="ServiceInfo" value="0,0,300,30"/>
		<parameter name="ServiceInfoLeft" value="0,0,300,30"/>
		<parameter name="ServiceInfoRight" value="300,0,600,30"/>
		<parameter name="ServiceInfoFont" value="screen_text;20"/>
		<parameter name="VirtualKeyBoard" value="45,45"/>
		<parameter name="VirtualKeyBoardAlignment" value="0,0"/>
		<parameter name="VirtualKeyBoardPadding" value="4,4"/>
<!-- cf#_#stop -->
		<parameter name="VirtualKeyBoardShiftColors" value="0x00ffffff,0x00ffffff,0x0000ffff,0x00ff00ff"/>
<!-- cf#_#start -->
		<parameter name="PiconManagerList" value="10,0,1120,30"/>
		<parameter name="PiconManagerListFont" value="screen_text;20"/>
		<parameter name="ProgrammlistenUpdaterList" value="10,8,480,200,40"/>
		<parameter name="ProgrammlistenUpdaterListFont" value="screen_text;22"/>
		<parameter name="EpgListMulti" value="160,110,76,10"/>
<!-- cf#_#rename -->
		<parameter name="EpgListMultiProgressBar" value="70,10,1"/>
<!-- cf#_#rename -->
		<parameter name="EpgListMultiProgressBar#_FHDscreen" value="105,15,1"/>
<!-- cf#_#rename -->
		<parameter name="EpgListIcon" value="1,10,21,21,1"/>
<!-- cf#_#rename -->
		<parameter name="EpgListIcon#_FHDscreen" value="2,12,25,25,2"/>
<!-- cf#_#rename -->
		<parameter name="EpgListSingle" value="60,156"/>
<!-- cf#_#rename -->
		<parameter name="EpgListSingle#_FHDscreen" value="88,220"/>
<!-- cf#_#start -->
		<parameter name="InformationColors" value="0x00ffffff,0x00ffffff,0x00ffffff,0x00cccccc,0x00cccccc,0x00ffffff,0x0000ffff"/>
	</parameters>
<!-- SKINFILES -->
	<include filename="/usr/share/enigma2/MetrixHD/skinfiles/skin_unchecked.xml" />
	<include filename="/usr/share/enigma2/MetrixHD/skinfiles/skin_templates.xml" />
	<include filename="/usr/share/enigma2/MetrixHD/skinfiles/skin_design.xml" />
	<include filename="/usr/share/enigma2/MetrixHD/skinfiles/skin_infobar.xml" />
	<include filename="/usr/share/enigma2/MetrixHD/skinfiles/skin_infobarlite.xml" />
	<include filename="/usr/share/enigma2/MetrixHD/skinfiles/skin_secondinfobar.xml" />
	<include filename="/usr/share/enigma2/MetrixHD/skinfiles/skin_secondinfobarecm.xml" />
	<include filename="/usr/share/enigma2/MetrixHD/skinfiles/skin_channelselection.xml" />
	<include filename="/usr/share/enigma2/MetrixHD/skinfiles/skin_openatv.xml" />
	<include filename="/usr/share/enigma2/MetrixHD/skinfiles/skin_plugins.xml" />
	<include filename="/usr/share/enigma2/MetrixHD/skinfiles/skin_movieplayer.xml" />
	<include filename="/usr/share/enigma2/MetrixHD/skinfiles/skin_emc.xml" />
<!-- SKINFILES -->
</skin>
